setup.py
kdcld/__init__.py
kdcld/cld.py
kdcld.egg-info/PKG-INFO
kdcld.egg-info/SOURCES.txt
kdcld.egg-info/dependency_links.txt
kdcld.egg-info/entry_points.txt
kdcld.egg-info/top_level.txt