Metadata-Version: 1.0
Name: kdcld
Version: 0.1.3
Summary: 命令行词典
Home-page: UNKNOWN
Author: kindan
Author-email: kind4n@gmail.com
License: UNKNOWN
Platform: UNKNOWN
